RoCloud/__init__.py
RoCloud-0.0.0.dist-info/LICENSE
RoCloud-0.0.0.dist-info/METADATA
RoCloud-0.0.0.dist-info/WHEEL
RoCloud-0.0.0.dist-info/top_level.txt
RoCloud-0.0.0.dist-info/RECORD
