Metadata-Version: 2.1
Name: RoCloud
Version: 0.0.0
Summary: Coming soon
Author-email: Tanay <tanaymaganti@gmail.com>
License-File: LICENSE
